nettigo_air_monitor/__init__.py
nettigo_air_monitor/const.py
nettigo_air_monitor/exceptions.py
nettigo_air_monitor/model.py
nettigo_air_monitor/py.typed
nettigo_air_monitor-5.0.0.dist-info/licenses/LICENSE
nettigo_air_monitor-5.0.0.dist-info/METADATA
nettigo_air_monitor-5.0.0.dist-info/WHEEL
nettigo_air_monitor-5.0.0.dist-info/top_level.txt
nettigo_air_monitor-5.0.0.dist-info/RECORD
