Metadata-Version: 2.4
Name: nettigo_air_monitor
Version: 5.0.0
Summary: Python wrapper for getting air quality data from Nettigo Air Monitor devices.
Author: Maciej Bieniek
License-Expression: Apache-2.0
Project-URL: Homepage, https://github.com/bieniu/nettigo-air-monitor
Classifier: Development Status :: 5 - Production/Stable
Classifier: Operating System :: OS Independent
Classifier: Programming Language :: Python
Classifier: Programming Language :: Python :: 3
Classifier: Programming Language :: Python :: 3.12
Classifier: Programming Language :: Python :: 3.13
Classifier: Programming Language :: Python :: 3 :: Only
Classifier: Typing :: Typed
Requires-Python: >=3.12
License-File: LICENSE
Requires-Dist: aiohttp>=3.9.4
Requires-Dist: aqipy-atmotech
Requires-Dist: dacite>=1.7.0
Requires-Dist: tenacity
Provides-Extra: test
Requires-Dist: aioresponses==0.7.8; extra == "test"
Requires-Dist: coverage==7.9.1; extra == "test"
Requires-Dist: mypy==1.16.1; extra == "test"
Requires-Dist: pytest-asyncio==1.0.0; extra == "test"
Requires-Dist: pytest-cov>=2.12.1; extra == "test"
Requires-Dist: pytest-error-for-skips==2.0.2; extra == "test"
Requires-Dist: pytest-timeout==2.4.0; extra == "test"
Requires-Dist: pytest==8.4.1; extra == "test"
Requires-Dist: ruff==0.12.1; extra == "test"
Requires-Dist: syrupy==4.9.1; extra == "test"
Provides-Extra: dev
Requires-Dist: pre-commit==4.2.0; extra == "dev"
Dynamic: license-file
